py_jdplayss/__init__.py
py_jdplayss/jdplay_telnet.py
py_jdplayss-0.0.2.dist-info/LICENSE
py_jdplayss-0.0.2.dist-info/METADATA
py_jdplayss-0.0.2.dist-info/WHEEL
py_jdplayss-0.0.2.dist-info/top_level.txt
py_jdplayss-0.0.2.dist-info/RECORD
